pymarketwatch/__init__.py
pymarketwatch-1.5.0.dist-info/LICENSE
pymarketwatch-1.5.0.dist-info/METADATA
pymarketwatch-1.5.0.dist-info/WHEEL
pymarketwatch-1.5.0.dist-info/top_level.txt
pymarketwatch-1.5.0.dist-info/RECORD
