Metadata-Version: 2.1
Name: pymarketwatch
Version: 1.5.0
Summary: API to interact with MarketWatch's Stock Market Game API
Home-page: https://github.com/bwees/pymarketwatch
Author: bwees
Author-email: brandonwees@gmail.com
License: Apache 2.0
Platform: UNKNOWN
Classifier: Programming Language :: Python :: 3
Classifier: Programming Language :: Python :: 3.7
License-File: LICENSE
Requires-Dist: beautifulsoup4
Requires-Dist: requests
